ORTEIL_IDLE_GAME_MAKER_CODE_GENERATOR/orteil_idle_game_maker_code_generator.py
ORTEIL_IDLE_GAME_MAKER_CODE_GENERATOR-1.2.dist-info/LICENSE
ORTEIL_IDLE_GAME_MAKER_CODE_GENERATOR-1.2.dist-info/METADATA
ORTEIL_IDLE_GAME_MAKER_CODE_GENERATOR-1.2.dist-info/WHEEL
ORTEIL_IDLE_GAME_MAKER_CODE_GENERATOR-1.2.dist-info/entry_points.txt
ORTEIL_IDLE_GAME_MAKER_CODE_GENERATOR-1.2.dist-info/top_level.txt
ORTEIL_IDLE_GAME_MAKER_CODE_GENERATOR-1.2.dist-info/RECORD
