Metadata-Version: 2.1
Name: ORTEIL-IDLE-GAME-MAKER-CODE-GENERATOR
Version: 1.2
Summary: This package contains implementation of the tool "ORTEIL_IDLE_GAME_MAKER_CODE_GENERATOR".
Home-page: https://github.com/GlobalCreativeCommunityFounder/ORTEIL_IDLE_GAME_MAKER_CODE_GENERATOR
Author: GlobalCreativeCommunityFounder
Author-email: globalcreativecommunityfounder@gmail.com
License: MIT
Platform: UNKNOWN
Classifier: Programming Language :: Python :: 3
Classifier: Programming Language :: Python :: 3.7
